pycramer-0.2.0.dist-info/WHEEL
pycramer-0.2.0.dist-info/top_level.txt
pycramer-0.2.0.dist-info/METADATA
pycramer-0.2.0.dist-info/RECORD
pycramer-0.2.0.dist-info/licenses/LICENCE
pycramer/_lookup.cpython-310-x86_64-linux-gnu.so
pycramer/_lookup.cpp
pycramer/__init__.py
pycramer/cramer.py
