Metadata-Version: 2.4
Name: pycramer
Version: 0.2.0
Summary: Cramér two-sample test for univariate and multivariate datasets in Python.
Author: Logan Sizemore
License:                     GNU GENERAL PUBLIC LICENSE
Project-URL: Homepage, https://github.com/sizemore0125/pycramer
Project-URL: Changelog, https://github.com/sizemore0125/pycramer/blob/main/cramer/CHANGES
Project-URL: Issues, https://github.com/sizemore0125/pycramer/issues
Keywords: statistics,cramer,two-sample,nonparametric
Classifier: Intended Audience :: Science/Research
Classifier: License :: OSI Approved :: GNU General Public License v3 (GPLv3)
Classifier: Programming Language :: Python :: 3
Classifier: Programming Language :: Python :: 3.10
Classifier: Programming Language :: Python :: 3.11
Classifier: Programming Language :: Python :: 3.12
Classifier: Programming Language :: C++
Classifier: Topic :: Scientific/Engineering :: Mathematics
Requires-Python: >=3.10
License-File: LICENCE
Requires-Dist: numpy>=1.23
Dynamic: license-file
